CorState/CorStateError.py
CorState/State.py
CorState/StateMachine.py
CorState/Transition.py
CorState/__init__.py
corstate-0.1.6.dev0.dist-info/licenses/LICENSE
corstate-0.1.6.dev0.dist-info/METADATA
corstate-0.1.6.dev0.dist-info/WHEEL
corstate-0.1.6.dev0.dist-info/top_level.txt
corstate-0.1.6.dev0.dist-info/RECORD
