Metadata-Version: 2.4
Name: CorState
Version: 0.1.6.dev0
Summary: Lightweight and versatile State Machine library
Home-page: https://github.com/Zentetsu/CorState
Author: Zentetsu
License: GPLv3
Requires-Python: >=3.8
License-File: LICENSE
Dynamic: author
Dynamic: description
Dynamic: description-content-type
Dynamic: home-page
Dynamic: license
Dynamic: license-file
Dynamic: requires-python
Dynamic: summary
